quantumsculpt/__init__.py
quantumsculpt/_version.py
quantumsculpt/blenderrender.py
quantumsculpt/cohp.py
quantumsculpt/colors.py
quantumsculpt/constants.py
quantumsculpt/dos.py
quantumsculpt/wavecar.py
quantumsculpt/blender/blender_render_molecule.py
quantumsculpt/featurefinder/__init__.py
quantumsculpt/featurefinder/peakfeatures.py
quantumsculpt/plotting/__init__.py
quantumsculpt/plotting/cohpplotting.py
quantumsculpt/plotting/dosplotting.py
quantumsculpt/plotting/integration.py
quantumsculpt/plotting/plotdecorators.py
quantumsculpt-0.2.0.dist-info/LICENSE
quantumsculpt-0.2.0.dist-info/METADATA
quantumsculpt-0.2.0.dist-info/WHEEL
quantumsculpt-0.2.0.dist-info/top_level.txt
quantumsculpt-0.2.0.dist-info/RECORD
